Attachments/AttachmentCategories.py
Attachments/Documents.py
Attachments/FileProcessingMethods.py
Attachments/FileProcessor.py
PineconeIngestion/PineconeOperations.py
PineconeIngestion/SharePoint.py
SharepointConnect/Authorization.py
SharepointConnect/CherwellIngestion.py
SharepointConnect/Drives.py
SharepointConnect/Files.py
SharepointConnect/Lists.py
SharepointConnect/Pages.py
SharepointConnect/Processor.py
SharepointConnect/SharePointAPI.py
SharepointConnect/Sites.py
SharepointConnect/WebParts.py
SharepointConnect/Models/AuthorizationInfo.py
SharepointConnect/Models/CherwellAuthorization.py
SharepointConnect/Models/CherwellStoredSearch.py
SharepointConnect/Models/Ingest.py
SharepointConnect/Models/IngestCherwell.py
SharepointConnect/Models/RezolveInfo.py
SharepointConnect/Models/SharepointDrives.py
SharepointConnect/Models/SharepointIds.py
SharepointConnect/Models/SharepointPages.py
SharepointConnect/Models/SharepointSites.py
utils/sharepoint_functions.py
utils/text_treatment.py
rezolve_ai_ingestion-0.1.4.dist-info/LICENSE
rezolve_ai_ingestion-0.1.4.dist-info/METADATA
rezolve_ai_ingestion-0.1.4.dist-info/WHEEL
rezolve_ai_ingestion-0.1.4.dist-info/top_level.txt
rezolve_ai_ingestion-0.1.4.dist-info/RECORD
