Metadata-Version: 2.1
Name: rezolve_ai_ingestion
Version: 0.1.4
Summary: A private package for ingesting and processing SharePoint data with AI capabilities
Author-email: Joshua O'Brien <josh@rezolve.ai>, Kushagra Kesarwani <kushagra.kessarwani@rezolve.ai>
License: Proprietary and Confidential
Project-URL: Homepage, https://your-private-repo-url.com/rezolve-ai-ingestion
Project-URL: Repository, https://your-private-repo-url.com/rezolve-ai-ingestion.git
Keywords: sharepoint,ai,ingestion,data processing,rezolve
Classifier: Development Status :: 1 - Planning
Classifier: Programming Language :: Python
Classifier: Programming Language :: Python :: 3
Classifier: Programming Language :: Python :: 3.7
Classifier: Programming Language :: Python :: 3.8
Classifier: Programming Language :: Python :: 3.9
Classifier: Programming Language :: Python :: 3.10
Classifier: Programming Language :: Python :: 3 :: Only
Requires-Python: >=3.7
License-File: LICENSE
Requires-Dist: annotated-types==0.7.0
Requires-Dist: anyio==4.6.0
Requires-Dist: argcomplete==1.10.3
Requires-Dist: asttokens==2.4.1
Requires-Dist: beautifulsoup4==4.8.2
Requires-Dist: certifi==2024.8.30
Requires-Dist: cffi==1.17.1
Requires-Dist: chardet==3.0.4
Requires-Dist: charset-normalizer==3.3.2
Requires-Dist: click==8.1.7
Requires-Dist: comm==0.2.2
Requires-Dist: compressed-rtf==1.0.6
Requires-Dist: cryptography==43.0.1
Requires-Dist: debugpy==1.8.6
Requires-Dist: decorator==5.1.1
Requires-Dist: distro==1.9.0
Requires-Dist: docx2txt==0.8
Requires-Dist: ebcdic==1.1.1
Requires-Dist: executing==2.1.0
Requires-Dist: extract-msg==0.28.7
Requires-Dist: h11==0.14.0
Requires-Dist: httpcore==1.0.5
Requires-Dist: httpx==0.27.2
Requires-Dist: idna==3.10
Requires-Dist: IMAPClient==2.1.0
Requires-Dist: ipykernel==6.29.5
Requires-Dist: ipython==8.27.0
Requires-Dist: jedi==0.19.1
Requires-Dist: jiter==0.5.0
Requires-Dist: joblib==1.4.2
Requires-Dist: jsonpatch==1.33
Requires-Dist: jsonpointer==3.0.0
Requires-Dist: langchain-core==0.3.6
Requires-Dist: langchain-text-splitters==0.3.0
Requires-Dist: langsmith==0.1.128
Requires-Dist: lxml==5.3.0
Requires-Dist: matplotlib-inline==0.1.7
Requires-Dist: msal==1.31.0
Requires-Dist: nest-asyncio==1.6.0
Requires-Dist: nltk==3.9.1
Requires-Dist: numpy==2.1.1
Requires-Dist: olefile==0.47
Requires-Dist: openai==1.48.0
Requires-Dist: opencv-python==4.10.0.84
Requires-Dist: orjson==3.10.7
Requires-Dist: packaging==24.1
Requires-Dist: pandas==2.2.3
Requires-Dist: parso==0.8.4
Requires-Dist: pdfminer.six==20191110
Requires-Dist: pexpect==4.9.0
Requires-Dist: pillow==10.4.0
Requires-Dist: pinecone==5.3.1
Requires-Dist: pinecone-plugin-inference==1.1.0
Requires-Dist: pinecone-plugin-interface==0.0.7
Requires-Dist: platformdirs==4.3.6
Requires-Dist: prompt-toolkit==3.0.48
Requires-Dist: psutil==6.0.0
Requires-Dist: ptyprocess==0.7.0
Requires-Dist: pure-eval==0.2.3
Requires-Dist: pycparser==2.22
Requires-Dist: pycryptodome==3.20.0
Requires-Dist: pydantic==2.9.2
Requires-Dist: pydantic-core==2.23.4
Requires-Dist: Pygments==2.18.0
Requires-Dist: PyJWT==2.9.0
Requires-Dist: PyMuPDF==1.24.10
Requires-Dist: python-dateutil==2.9.0.post0
Requires-Dist: python-docx==1.1.2
Requires-Dist: python-pptx==0.6.23
Requires-Dist: pytz==2024.2
Requires-Dist: PyYAML==6.0.2
Requires-Dist: pyzmq==26.2.0
Requires-Dist: regex==2024.9.11
Requires-Dist: requests==2.32.3
Requires-Dist: six==1.16.0
Requires-Dist: sniffio==1.3.1
Requires-Dist: sortedcontainers==2.4.0
Requires-Dist: soupsieve==2.6
Requires-Dist: SpeechRecognition==3.8.1
Requires-Dist: stack-data==0.6.3
Requires-Dist: tenacity==8.5.0
Requires-Dist: tornado==6.4.1
Requires-Dist: tqdm==4.66.5
Requires-Dist: traitlets==5.14.3
Requires-Dist: typing-extensions==4.12.2
Requires-Dist: tzdata==2024.2
Requires-Dist: tzlocal==5.2
Requires-Dist: urllib3==2.2.3
Requires-Dist: wcwidth==0.2.13
Requires-Dist: xlrd==1.2.0
Requires-Dist: XlsxWriter==3.2.0
Provides-Extra: textract
Requires-Dist: textract==1.6.5; extra == "textract"
Requires-Dist: extract-msg==0.28.7; extra == "textract"
Requires-Dist: beautifulsoup4==4.8.2; extra == "textract"
Requires-Dist: six==1.12.0; extra == "textract"
